flask_httpx_request_converted_to_flask_test_client_request/__init__.py
flask_httpx_request_converted_to_flask_test_client_request-0.1.5.dist-info/LICENSE
flask_httpx_request_converted_to_flask_test_client_request-0.1.5.dist-info/METADATA
flask_httpx_request_converted_to_flask_test_client_request-0.1.5.dist-info/WHEEL
flask_httpx_request_converted_to_flask_test_client_request-0.1.5.dist-info/top_level.txt
flask_httpx_request_converted_to_flask_test_client_request-0.1.5.dist-info/RECORD
