Metadata-Version: 2.1
Name: flask-httpx-request-converted-to-flask-test-client-request
Version: 0.1.5
Summary: Unittest Tool: This is a `flask.test_client_class` I wrote to making the libraries created by `openapi-python-client` work with `flask.test_client()`
Home-page: https://github.com/dvaerum/flask-httpx-request-converted-to-flask-test-client-requests
Author: Dennis Vestergaard Værum
Author-email: convert_httpx_2_flask_test_client@varum.dk
License: 0BSD
Classifier: Programming Language :: Python :: 3
Classifier: License :: OSI Approved :: BSD License
Classifier: Operating System :: OS Independent
Requires-Python: >=3.6
License-File: LICENSE
